{
    "name": "Aegis",
    "tree": {
        "$className": "DataModel",

        "ReplicatedStorage": {
            "$className": "ReplicatedStorage",
            
            "Aegis": {
                "$path": "src"
            },
            
            "TestEZ": {
                "$path": "modules/testez"
            }
        },

        "HttpService": {
            "$className": "HttpService",
            "$properties": {
                "HttpEnabled": true
            }
        },
        
        "Players": {
            "$className": "Players",
            "$properties": {
                "CharacterAutoLoads": false
            }
        }
    }
}